{"namedChunkGroups":{"polyfill":{"name":"polyfill","assets":[{"name":"webpack-runtime-8f67b1e1eca7bf85b62b.js","size":2533},{"name":"polyfill-1b81a701d9240fc129ee.js","size":82831}],"filteredAssets":0,"assetsSize":85364,"filteredAuxiliaryAssets":2,"auxiliaryAssetsSize":211235},"app":{"name":"app","assets":[{"name":"webpack-runtime-8f67b1e1eca7bf85b62b.js","size":2533},{"name":"framework-c9647d0ea3403249b1ba.js","size":129752},{"name":"app-80fc56d7b612a4ff472b.js","size":925661}],"filteredAssets":0,"assetsSize":1057946,"filteredAuxiliaryAssets":4,"auxiliaryAssetsSize":4058343}},"assetsByChunkName":{"polyfill":["webpack-runtime-8f67b1e1eca7bf85b62b.js","polyfill-1b81a701d9240fc129ee.js"],"app":["webpack-runtime-8f67b1e1eca7bf85b62b.js","framework-c9647d0ea3403249b1ba.js","app-80fc56d7b612a4ff472b.js"]},"childAssetsByChunkName":{}}